<?xml version="1.0" encoding="UTF-8"?>
<!-- Foundation -->
<window id="0">
	<defaultcontrol always="true">310</defaultcontrol>
	<allowoverlay>yes</allowoverlay>
	<onload>AlarmClock(cyclenowplaying,Control.Move(9801,1),00:10,silent,loop)</onload>

	<controls>

		<include>GlobalBackground</include>
		<include>Home-BGFade</include>
		<include>Home-Fade</include>
		<include>Home-NavigationText</include>
		<include>Home-SubMenu</include>
		<include>Home-Menu</include>
		<include>Common-Items</include>

	</controls>

</window>